sysdweb
