Metadata-Version: 2.1
Name: sysdweb
Version: 1.1.7
Summary: Control systemd services through Web or REST API
Author-email: Óscar García Amor <ogarcia@connectical.com>
License:                     GNU GENERAL PUBLIC LICENSE
Project-URL: Bug Reports, https://github.com/ogarcia/sysdweb/issues
Project-URL: Source, https://github.com/ogarcia/sysdweb
Keywords: REST API,systemd
Classifier: Development Status :: 5 - Production/Stable
Classifier: Environment :: Web Environment
Classifier: Framework :: Bottle
Classifier: Intended Audience :: End Users/Desktop
Classifier: Intended Audience :: System Administrators
Classifier: License :: OSI Approved :: GNU General Public License v3 (GPLv3)
Classifier: Natural Language :: English
Classifier: Operating System :: POSIX :: Linux
Classifier: Programming Language :: Python :: 3
Classifier: Topic :: System
Classifier: Topic :: Utilities
Requires-Python: >=3.10
License-File: LICENSE
